COPYING
MANIFEST.in
README.rst
bootstrap.py
buildout.cfg
setup.py
xbob/__init__.py
xbob.db.voxforge.egg-info/PKG-INFO
xbob.db.voxforge.egg-info/SOURCES.txt
xbob.db.voxforge.egg-info/dependency_links.txt
xbob.db.voxforge.egg-info/entry_points.txt
xbob.db.voxforge.egg-info/namespace_packages.txt
xbob.db.voxforge.egg-info/not-zip-safe
xbob.db.voxforge.egg-info/requires.txt
xbob.db.voxforge.egg-info/top_level.txt
xbob/db/__init__.py
xbob/db/voxforge/__init__.py
xbob/db/voxforge/driver.py
xbob/db/voxforge/query.py
xbob/db/voxforge/test.py
xbob/db/voxforge/lists/list_of_tgz_files.lst
xbob/db/voxforge/lists/dev/for_models.lst
xbob/db/voxforge/lists/dev/for_probes.lst
xbob/db/voxforge/lists/eval/for_models.lst
xbob/db/voxforge/lists/eval/for_probes.lst
xbob/db/voxforge/lists/norm/train_optional_world_1.lst
xbob/db/voxforge/lists/norm/train_optional_world_2.lst
xbob/db/voxforge/lists/norm/train_world.lst