Metadata-Version: 1.1
Name: xbob.db.voxforge
Version: 0.1.0
Summary: Speaker verification protocol on a subset of the VoxForge database
Home-page: http://pypi.python.org/pypi/xbob.db.voxforge
Author: Elie Khoury
Author-email: Elie.Khoury@idiap.ch
License: GPLv3
Keywords: Speaker Recognition,Speaker verification,Gaussian Mixture Model,ISV,UBM-GMM,I-Vector,Audio processing,Database,Voxforge
Platform: UNKNOWN
Classifier: Development Status :: 4 - Beta
Classifier: Intended Audience :: Education
Classifier: License :: OSI Approved :: GNU General Public License v3 (GPLv3)
Classifier: Natural Language :: English
Classifier: Programming Language :: Python
Classifier: Programming Language :: Python :: 3
Classifier: Topic :: Scientific/Engineering :: Artificial Intelligence
Classifier: Topic :: Database :: Front-Ends
